ag_kafka_utils/__init__.py
ag_kafka_utils/admin.py
ag_kafka_utils/base.py
ag_kafka_utils/consumer.py
ag_kafka_utils/producer.py
ag_kafka_utils/test.py
ag_kafka_utils-0.1.2.dist-info/licenses/LICENSE
ag_kafka_utils-0.1.2.dist-info/METADATA
ag_kafka_utils-0.1.2.dist-info/WHEEL
ag_kafka_utils-0.1.2.dist-info/top_level.txt
ag_kafka_utils-0.1.2.dist-info/RECORD
