Metadata-Version: 2.4
Name: ag_kafka_utils
Version: 0.1.2
Summary: A package to address your problems
Author-email: Omid Karimzade <omidekz@gmail.com>
License: GNU GENERAL PUBLIC LICENSE
Project-URL: Homepage, https://github.com/yourname/myproject
Keywords: utils,kafka
Requires-Python: >=3.9
License-File: LICENSE
Requires-Dist: kafka-python==2.1.1
Requires-Dist: orjson==3.10.13
Requires-Dist: pydantic==2.10.4
Dynamic: license-file
